jaysun/__init__.py
jaysun/tools.py
jaysun-0.1.2.dist-info/LICENSE
jaysun-0.1.2.dist-info/METADATA
jaysun-0.1.2.dist-info/WHEEL
jaysun-0.1.2.dist-info/top_level.txt
jaysun-0.1.2.dist-info/RECORD
