Metadata-Version: 2.1
Name: jaysun
Version: 0.1.2
Summary: A small example package
Home-page: https://github.com/Sun-Wen-Jie/jaysun-plugin
Author: jaysun
Author-email: jaysun <jaysun1015@outlook.com>
License: MIT
Project-URL: Homepage, https://github.com/Sun-Wen-Jie/jaysun-plugin
Project-URL: Bug Tracker, https://github.com/Sun-Wen-Jie/jaysun-plugin/issues
Classifier: Programming Language :: Python :: 3
Classifier: License :: OSI Approved :: MIT License
Classifier: Operating System :: OS Independent
Requires-Python: >=3.7
License-File: LICENSE
Requires-Dist: PyYAML ==6.0
Requires-Dist: requests ==2.30.0
Requires-Dist: setuptools ==67.3.3
